09_FPGA-UART-Verification-cocotb/rtl/pwm_generator.vhd
library IEEE;
use IEEE.STD_LOGIC_1164.ALL;
use IEEE.NUMERIC_STD.ALL;

entity pwm_generator is
    port(
        clk : in std_logic;
        rst : in std_logic;
        duty_cycle : in std_logic_vector(6 downto 0);
        pwm_out : out std_logic
    );
end pwm_generator;

architecture Behavioral of pwm_generator is
    constant COUNTER_MAX : integer := 100;
    signal counter : integer range 0 to 99 := 0;
    signal duty_int : integer range 0 to 100;
    
begin
    duty_int <= to_integer(unsigned(duty_cycle));
    
    process(clk)
    begin
        if rising_edge(clk) then
            if rst = '1' then
                counter <= 0;
                pwm_out <= '0';
            else
                if counter = COUNTER_MAX - 1 then
                    counter <= 0;
                else
                    counter <= counter + 1;
                end if;
                
                if counter < duty_int then
                    pwm_out <= '1';
                else
                    pwm_out <= '0';
                end if;
            end if;
        end if;
    end process;
end Behavioral;

09_FPGA-UART-Verification-cocotb/rtl/pwm_generator_tb.vhd
library IEEE;
use IEEE.STD_LOGIC_1164.ALL;
use IEEE.NUMERIC_STD.ALL;

entity pwm_generator_tb is
end pwm_generator_tb;

architecture Behavioral of pwm_generator_tb is
    constant CLK_PERIOD : time := 83.333 ns;
    
    signal clk : std_logic := '0';
    signal rst : std_logic := '1';
    signal duty_cycle : std_logic_vector(6 downto 0) := (others => '0');
    signal pwm_out : std_logic;
    
    component pwm_generator
        port(
            clk : in std_logic;
            rst : in std_logic;
            duty_cycle : in std_logic_vector(6 downto 0);
            pwm_out : out std_logic
        );
    end component;
    
begin
    uut: pwm_generator
        port map(
            clk => clk,
            rst => rst,
            duty_cycle => duty_cycle,
            pwm_out => pwm_out
        );
    
    clk_process: process
    begin
        wait for CLK_PERIOD/2;
        clk <= not clk;
    end process;
    
    stim_proc: process
    begin
        wait for 1000 ns;
        rst <= '0';
        
        duty_cycle <= "0011001"; -- 25
        wait for 100 us;
        
        duty_cycle <= "0110010"; -- 50
        wait for 100 us;
        
        duty_cycle <= "1001011"; -- 75
        wait for 100 us;
        
        assert false report "Test: OK" severity note;
        wait;
    end process;
    
end Behavioral;

09_FPGA-UART-Verification-cocotb/resultats/pwm_waveform.vcd
$date
  Sun Mar 15 01:24:17 2026
$end
$version
  GHDL v0
$end
$timescale
  1 fs
$end
$scope module standard $end
$upscope $end
$scope module std_logic_1164 $end
$upscope $end
$scope module numeric_std $end
$upscope $end
$scope module pwm_generator_tb $end
$var reg 1 ! clk $end
$var reg 1 " rst $end
$var reg 7 # duty_cycle[6:0] $end
$var reg 1 $ pwm_out $end
$scope module uut $end
$var reg 1 % clk $end
$var reg 1 & rst $end
$var reg 7 ' duty_cycle[6:0] $end
$var reg 1 ( pwm_out $end
$var integer 32 ) counter $end
$var integer 32 * duty_int $end
$upscope $end
$upscope $end
$enddefinitions $end
#0
0!
1"
b0000000 #
U$
0%
1&
b0000000 '
U(
b0 )
b0 *
#41666500
1!
0$
1%
0(
#83333000
0!
0%
#124999500
1!
1%
#166666000
0!
0%
#208332500
1!
1%
#249999000
0!
0%
#291665500
1!
1%
#333332000
0!
0%
#374998500
1!
1%
#416665000
0!
0%
#458331500
1!
1%
#499998000
0!
0%
#541664500
1!
1%
#583331000
0!
0%
#624997500
1!
1%
#666664000
0!
0%
#708330500
1!
1%
#749997000
0!
0%
#791663500
1!
1%
#833330000
0!
0%
#874996500
1!
1%
#916663000
0!
0%
#958329500
1!
1%
#999996000
0!
0%
#1000000000
0"
b0011001 #
0&
b0011001 '
b11001 *
#1041662500
1!
1$
1%
1(
b1 )
#1083329000
0!
0%
#1124995500
1!
1%
b10 )
#1166662000
0!
0%
#1208328500
1!
1%
b11 )
#1249995000
0!
0%
#1291661500
1!
1%
b100 )
#1333328000
0!
0%
#1374994500
1!
1%
b101 )
#1416661000
0!
0%
#1458327500
1!
1%
b110 )
#1499994000
0!
0%
#1541660500
1!
1%
b111 )
#1583327000
0!
0%
#1624993500
1!
1%
b1000 )
#1666660000
0!
0%
#1708326500
1!
1%
b1001 )
#1749993000
0!
0%
#1791659500
1!
1%
b1010 )
#1833326000
0!
0%
#1874992500
1!
1%
b1011 )
#1916659000
0!
0%
#1958325500
1!
1%
b1100 )
#1999992000
0!
0%
#2041658500
1!
1%
b1101 )
#2083325000
0!
0%
#2124991500
1!
1%
b1110 )
#2166658000
0!
0%
#2208324500
1!
1%
b1111 )
#2249991000
0!
0%
#2291657500
1!
1%
b10000 )
#2333324000
0!
0%
#2374990500
1!
1%
b10001 )
#2416657000
0!
0%
#2458323500
1!
1%
b10010 )
#2499990000
0!
0%
#2541656500
1!
1%
b10011 )
#2583323000
0!
0%
#2624989500
1!
1%
b10100 )
#2666656000
0!
0%
#2708322500
1!
1%
b10101 )
#2749989000
0!
0%
#2791655500
1!
1%
b10110 )
#2833322000
0!
0%
#2874988500
1!
1%
b10111 )
#2916655000
0!
0%
#2958321500
1!
1%
b11000 )
#2999988000
0!
0%
#3041654500
1!
1%
b11001 )
#3083321000
0!
0%
#3124987500
1!
0$
1%
0(
b11010 )
#3166654000
0!
0%
#3208320500
1!
1%
b11011 )
#3249987000
0!
0%
#3291653500
1!
1%
b11100 )
#3333320000
0!
0%
#3374986500
1!
1%
b11101 )
#3416653000
0!
0%
#3458319500
1!
1%
b11110 )
#3499986000
0!
0%
#3541652500
1!
1%
b11111 )
#3583319000
0!
0%
#3624985500
1!
1%
b100000 )
#3666652000
0!
0%
#3708318500
1!
1%
b100001 )
#3749985000
0!
0%
#3791651500
1!
1%
b100010 )
#3833318000
0!
0%
#3874984500
1!
1%
b100011 )
#3916651000
0!
0%
#3958317500
1!
1%
b100100 )
#3999984000
0!
0%
#4041650500
1!
1%
b100101 )
#4083317000
0!
0%
#4124983500
1!
1%
b100110 )
#4166650000
0!
0%
#4208316500
1!
1%
b100111 )
#4249983000
0!
0%
#4291649500
1!
1%
b101000 )
#4333316000
0!
0%
#4374982500
1!
1%
b101001 )
#4416649000
0!
0%
#4458315500
1!
1%
b101010 )
#4499982000
0!
0%
#4541648500
1!
1%
b101011 )
#4583315000
0!
0%
#4624981500
1!
1%
b101100 )
#4666648000
0!
0%
#4708314500
1!
1%
b101101 )
#4749981000
0!
0%
#4791647500
1!
1%
b101110 )
#4833314000
0!
0%
#4874980500
1!
1%
b101111 )
#4916647000
0!
0%
#4958313500
1!
1%
b110000 )
#4999980000
0!
0%
#5041646500
1!
1%
b110001 )
#5083313000
0!
0%
#5124979500
1!
1%
b110010 )
#5166646000
0!
0%
#5208312500
1!
1%
b110011 )
#5249979000
0!
0%
#5291645500
1!
1%
b110100 )
#5333312000
0!
0%
#5374978500
1!
1%
b110101 )
#5416645000
0!
0%
#5458311500
1!
1%
b110110 )
#5499978000
0!
0%
#5541644500
1!
1%
b110111 )
#5583311000
0!
0%
#5624977500
1!
1%
b111000 )
#5666644000
0!
0%
#5708310500
1!
1%
b111001 )
#5749977000
0!
0%
#5791643500
1!
1%
b111010 )
#5833310000
0!
0%
#5874976500
1!
1%
b111011 )
#5916643000
0!
0%
#5958309500
1!
1%
b111100 )
#5999976000
0!
0%
#6041642500
1!
1%
b111101 )
#6083309000
0!
0%
#6124975500
1!
1%
b111110 )
#6166642000
0!
0%
#6208308500
1!
1%
b111111 )
#6249975000
0!
0%
#6291641500
1!
1%
b1000000 )
#6333308000
0!
0%
#6374974500
1!
1%
b1000001 )
#6416641000
0!
0%
#6458307500
1!
1%
b1000010 )
#6499974000
0!
0%
#6541640500
1!
1%
b1000011 )
#6583307000
0!
0%
#6624973500
1!
1%
b1000100 )
#6666640000
0!
0%
#6708306500
1!
1%
b1000101 )
#6749973000
0!
0%
#6791639500
1!
1%
b1000110 )
#6833306000
0!
0%
#6874972500
1!
1%
b1000111 )
#6916639000
0!
0%
#6958305500
1!
1%
b1001000 )
#6999972000
0!
0%
#7041638500
1!
1%
b1001001 )
#7083305000
0!
0%
#7124971500
1!
1%
b1001010 )
#7166638000
0!
0%
#7208304500
1!
1%
b1001011 )
#7249971000
0!
0%
#7291637500
1!
1%
b1001100 )
#7333304000
0!
0%
#7374970500
1!
1%
b1001101 )
#7416637000
0!
0%
#7458303500
1!
1%
b1001110 )
#7499970000
0!
0%
#7541636500
1!
1%
b1001111 )
#7583303000
0!
0%
#7624969500
1!
1%
b1010000 )
#7666636000
0!
0%
#7708302500
1!
1%
b1010001 )
#7749969000
0!
0%
#7791635500
1!
1%
b1010010 )
#7833302000
0!
0%
#7874968500
1!
1%
b1010011 )
#7916635000
0!
0%
#7958301500
1!
1%
b1010100 )
#7999968000
0!
0%
#8041634500
1!
1%
b1010101 )
#8083301000
0!
0%
#8124967500
1!
1%
b1010110 )
#8166634000
0!
0%
#8208300500
1!
1%
b1010111 )
#8249967000
0!
0%
#8291633500
1!
1%
b1011000 )
#8333300000
0!
0%
#8374966500
1!
1%
b1011001 )
#8416633000
0!
0%
#8458299500
1!
1%
b1011010 )
#8499966000
0!
0%
#8541632500
1!
1%
b1011011 )
#8583299000
0!
0%
#8624965500
1!
1%
b1011100 )
#8666632000
0!
0%
#8708298500
1!
1%
b1011101 )
#8749965000
0!
0%
#8791631500
1!
1%
b1011110 )
#8833298000
0!
0%
#8874964500
1!
1%
b1011111 )
#8916631000
0!
0%
#8958297500
1!
1%
b1100000 )
#8999964000
0!
0%
#9041630500
1!
1%
b1100001 )
#9083297000
0!
0%
#9124963500
1!
1%
b1100010 )
#9166630000
0!
0%
#9208296500
1!
1%
b1100011 )
#9249963000
0!
0%
#9291629500
1!
1%
b0 )
#9333296000
0!
0%
#9374962500
1!
1$
1%
1(
b1 )
#9416629000
0!
0%
#9458295500
1!
1%
b10 )
#9499962000
0!
0%
#9541628500
1!
1%
b11 )
#9583295000
0!
0%
#9624961500
1!
1%
b100 )
#9666628000
0!
0%
#9708294500
1!
1%
b101 )
#9749961000
0!
0%
#9791627500
1!
1%
b110 )
#9833294000
0!
0%
#9874960500
1!
1%
b111 )
#9916627000
0!
0%
#9958293500
1!
1%
b1000 )
#9999960000
0!
0%
#10041626500
1!
1%
b1001 )
#10083293000
0!
0%
#10124959500
1!
1%
b1010 )
#10166626000
0!
0%
#10208292500
1!
1%
b1011 )
#10249959000
0!
0%
#10291625500
1!
1%
b1100 )
#10333292000
0!
0%
#10374958500
1!
1%
b1101 )
#10416625000
0!
0%
#10458291500
1!
1%
b1110 )
#10499958000
0!
0%
#10541624500
1!
1%
b1111 )
#10583291000
0!
0%
#10624957500
1!
1%
b10000 )
#10666624000
0!
0%
#10708290500
1!
1%
b10001 )
#10749957000
0!
0%
#10791623500
1!
1%
b10010 )
#10833290000
0!
0%
#10874956500
1!
1%
b10011 )
#10916623000
0!
0%
#10958289500
1!
1%
b10100 )
#10999956000
0!
0%
#11041622500
1!
1%
b10101 )
#11083289000
0!
0%
#11124955500
1!
1%
b10110 )
#11166622000
0!
0%
#11208288500
1!
1%
b10111 )
#11249955000
0!
0%
#11291621500
1!
1%
b11000 )
#11333288000
0!
0%
#11374954500
1!
1%
b11001 )
#11416621000
0!
0%
#11458287500
1!
0$
1%
0(
b11010 )
#11499954000
0!
0%
#11541620500
1!
1%
b11011 )
#11583287000
0!
0%
#11624953500
1!
1%
b11100 )
#11666620000
0!
0%
#11708286500
1!
1%
b11101 )
#11749953000
0!
0%
#11791619500
1!
1%
b11110 )
#11833286000
0!
0%
#11874952500
1!
1%
b11111 )
#11916619000
0!
0%
#11958285500
1!
1%
b100000 )
#11999952000
0!
0%
#12041618500
1!
1%
b100001 )
#12083285000
0!
0%
#12124951500
1!
1%
b100010 )
#12166618000
0!
0%
#12208284500
1!
1%
b100011 )
#12249951000
0!
0%
#12291617500
1!
1%
b100100 )
#12333284000
0!
0%
#12374950500
1!
1%
b100101 )
#12416617000
0!
0%
#12458283500
1!
1%
b100110 )
#12499950000
0!
0%
#12541616500
1!
1%
b100111 )
#12583283000
0!
0%
#12624949500
1!
1%
b101000 )
#12666616000
0!
0%
#12708282500
1!
1%
b101001 )
#12749949000
0!
0%
#12791615500
1!
1%
b101010 )
#12833282000
0!
0%
#12874948500
1!
1%
b101011 )
#12916615000
0!
0%
#12958281500
1!
1%
b101100 )
#12999948000
0!
0%
#13041614500
1!
1%
b101101 )
#13083281000
0!
0%
#13124947500
1!
1%
b101110 )
#13166614000
0!
0%
#13208280500
1!
1%
b101111 )
#13249947000
0!
0%
#13291613500
1!
1%
b110000 )
#13333280000
0!
0%
#13374946500
1!
1%
b110001 )
#13416613000
0!
0%
#13458279500
1!
1%
b110010 )
#13499946000
0!
0%
#13541612500
1!
1%
b110011 )
#13583279000
0!
0%
#13624945500
1!
1%
b110100 )
#13666612000
0!
0%
#13708278500
1!
1%
b110101 )
#13749945000
0!
0%
#13791611500
1!
1%
b110110 )
#13833278000
0!
0%
#13874944500
1!
1%
b110111 )
#13916611000
0!
0%
#13958277500
1!
1%
b111000 )
#13999944000
0!
0%
#14041610500
1!
1%
b111001 )
#14083277000
0!
0%
#14124943500
1!
1%
b111010 )
#14166610000
0!
0%
#14208276500
1!
1%
b111011 )
#14249943000
0!
0%
#14291609500
1!
1%
b111100 )
#14333276000
0!
0%
#14374942500
1!
1%
b111101 )
#14416609000
0!
0%
#14458275500
1!
1%
b111110 )
#14499942000
0!
0%
#14541608500
1!
1%
b111111 )
#14583275000
0!
0%
#14624941500
1!
1%
b1000000 )
#14666608000
0!
0%
#14708274500
1!
1%
b1000001 )
#14749941000
0!
0%
#14791607500
1!
1%
b1000010 )
#14833274000
0!
0%
#14874940500
1!
1%
b1000011 )
#14916607000
0!
0%
#14958273500
1!
1%
b1000100 )
#14999940000
0!
0%
#15041606500
1!
1%
b1000101 )
#15083273000
0!
0%
#15124939500
1!
1%
b1000110 )
#15166606000
0!
0%
#15208272500
1!
1%
b1000111 )
#15249939000
0!
0%
#15291605500
1!
1%
b1001000 )
#15333272000
0!
0%
#15374938500
1!
1%
b1001001 )
#15416605000
0!
0%
#15458271500
1!
1%
b1001010 )
#15499938000
0!
0%
#15541604500
1!
1%
b1001011 )
#15583271000
0!
0%
#15624937500
1!
1%
b1001100 )
#15666604000
0!
0%
#15708270500
1!
1%
b1001101 )
#15749937000
0!
0%
#15791603500
1!
1%
b1001110 )
#15833270000
0!
0%
#15874936500
1!
1%
b1001111 )
#15916603000
0!
0%
#15958269500
1!
1%
b1010000 )
#15999936000
0!
0%
#16041602500
1!
1%
b1010001 )
#16083269000
0!
0%
#16124935500
1!
1%
b1010010 )
#16166602000
0!
0%
#16208268500
1!
1%
b1010011 )
#16249935000
0!
0%
#16291601500
1!
1%
b1010100 )
#16333268000
0!
0%
#16374934500
1!
1%
b1010101 )
#16416601000
0!
0%
#16458267500
1!
1%
b1010110 )
#16499934000
0!
0%
#16541600500
1!
1%
b1010111 )
#16583267000
0!
0%
#16624933500
1!
1%
b1011000 )
#16666600000
0!
0%
#16708266500
1!
1%
b1011001 )
#16749933000
0!
0%
#16791599500
1!
1%
b1011010 )
#16833266000
0!
0%
#16874932500
1!
1%
b1011011 )
#16916599000
0!
0%
#16958265500
1!
1%
b1011100 )
#16999932000
0!
0%
#17041598500
1!
1%
b1011101 )
#17083265000
0!
0%
#17124931500
1!
1%
b1011110 )
#17166598000
0!
0%
#17208264500
1!
1%
b1011111 )
#17249931000
0!
0%
#17291597500
1!
1%
b1100000 )
#17333264000
0!
0%
#17374930500
1!
1%
b1100001 )
#17416597000
0!
0%
#17458263500
1!
1%
b1100010 )
#17499930000
0!
0%
#17541596500
1!
1%
b1100011 )
#17583263000
0!
0%
#17624929500
1!
1%
b0 )
#17666596000
0!
0%
#17708262500
1!
1$
1%
1(
b1 )
#17749929000
0!
0%
#17791595500
1!
1%
b10 )
#17833262000
0!
0%
#17874928500
1!
1%
b11 )
#17916595000
0!
0%
#17958261500
1!
1%
b100 )
#17999928000
0!
0%
#18041594500
1!
1%
b101 )
#18083261000
0!
0%
#18124927500
1!
1%
b110 )
#18166594000
0!
0%
#18208260500
1!
1%
b111 )
#18249927000
0!
0%
#18291593500
1!
1%
b1000 )
#18333260000
0!
0%
#18374926500
1!
1%
b1001 )
#18416593000
0!
0%
#18458259500
1!
1%
b1010 )
#18499926000
0!
0%
#18541592500
1!
1%
b1011 )
#18583259000
0!
0%
#18624925500
1!
1%
b1100 )
#18666592000
0!
0%
#18708258500
1!
1%
b1101 )
#18749925000
0!
0%
#18791591500
1!
1%
b1110 )
#18833258000
0!
0%
#18874924500
1!
1%
b1111 )
#18916591000
0!
0%
#18958257500
1!
1%
b10000 )
#18999924000
0!
0%
#19041590500
1!
1%
b10001 )
#19083257000
0!
0%
#19124923500
1!
1%
b10010 )
#19166590000
0!
0%
#19208256500
1!
1%
b10011 )
#19249923000
0!
0%
#19291589500
1!
1%
b10100 )
#19333256000
0!
0%
#19374922500
1!
1%
b10101 )
#19416589000
0!
0%
#19458255500
1!
1%
b10110 )
#19499922000
0!
0%
#19541588500
1!
1%
b10111 )
#19583255000
0!
0%
#19624921500
1!
1%
b11000 )
#19666588000
0!
0%
#19708254500
1!
1%
b11001 )
#19749921000
0!
0%
#19791587500
1!
0$
1%
0(
b11010 )
#19833254000
0!
0%
#19874920500
1!
1%
b11011 )
#19916587000
0!
0%
#19958253500
1!
1%
b11100 )
#19999920000
0!
0%
#20041586500
1!
1%
b11101 )
#20083253000
0!
0%
#20124919500
1!
1%
b11110 )
#20166586000
0!
0%
#20208252500
1!
1%
b11111 )
#20249919000
0!
0%
#20291585500
1!
1%
b100000 )
#20333252000
0!
0%
#20374918500
1!
1%
b100001 )
#20416585000
0!
0%
#20458251500
1!
1%
b100010 )
#20499918000
0!
0%
#20541584500
1!
1%
b100011 )
#20583251000
0!
0%
#20624917500
1!
1%
b100100 )
#20666584000
0!
0%
#20708250500
1!
1%
b100101 )
#20749917000
0!
0%
#20791583500
1!
1%
b100110 )
#20833250000
0!
0%
#20874916500
1!
1%
b100111 )
#20916583000
0!
0%
#20958249500
1!
1%
b101000 )
#20999916000
0!
0%
#21041582500
1!
1%
b101001 )
#21083249000
0!
0%
#21124915500
1!
1%
b101010 )
#21166582000
0!
0%
#21208248500
1!
1%
b101011 )
#21249915000
0!
0%
#21291581500
1!
1%
b101100 )
#21333248000
0!
0%
#21374914500
1!
1%
b101101 )
#21416581000
0!
0%
#21458247500
1!
1%
b101110 )
#21499914000
0!
0%
#21541580500
1!
1%
b101111 )
#21583247000
0!
0%
#21624913500
1!
1%
b110000 )
#21666580000
0!
0%
#21708246500
1!
1%
b110001 )
#21749913000
0!
0%
#21791579500
1!
1%
b110010 )
#21833246000
0!
0%
#21874912500
1!
1%
b110011 )
#21916579000
0!
0%
#21958245500
1!
1%
b110100 )
#21999912000
0!
0%
#22041578500
1!
1%
b110101 )
#22083245000
0!
0%
#22124911500
1!
1%
b110110 )
#22166578000
0!
0%
#22208244500
1!
1%
b110111 )
#22249911000
0!
0%
#22291577500
1!
1%
b111000 )
#22333244000
0!
0%
#22374910500
1!
1%
b111001 )
#22416577000
0!
0%
#22458243500
1!
1%
b111010 )
#22499910000
0!
0%
#22541576500
1!
1%
b111011 )
#22583243000
0!
0%
#22624909500
1!
1%
b111100 )
#22666576000
0!
0%
#22708242500
1!
1%
b111101 )
#22749909000
0!
0%
#22791575500
1!
1%
b111110 )
#22833242000
0!
0%
#22874908500
1!
1%
b111111 )
#22916575000
0!
0%
#22958241500
1!
1%
b1000000 )
#22999908000
0!
0%
#23041574500
1!
1%
b1000001 )
#23083241000
0!
0%
#23124907500
1!
1%
b1000010 )
#23166574000
0!
0%
#23208240500
1!
1%
b1000011 )
#23249907000
0!
0%
#23291573500
1!
1%
b1000100 )
#23333240000
0!
0%
#23374906500
1!
1%
b1000101 )
#23416573000
0!
0%
#23458239500
1!
1%
b1000110 )
#23499906000
0!
0%
#23541572500
1!
1%
b1000111 )
#23583239000
0!
0%
#23624905500
1!
1%
b1001000 )
#23666572000
0!
0%
#23708238500
1!
1%
b1001001 )
#23749905000
0!
0%
#23791571500
1!
1%
b1001010 )
#23833238000
0!
0%
#23874904500
1!
1%
b1001011 )
#23916571000
0!
0%
#23958237500
1!
1%
b1001100 )
#23999904000
0!
0%
#24041570500
1!
1%
b1001101 )
#24083237000
0!
0%
#24124903500
1!
1%
b1001110 )
#24166570000
0!
0%
#24208236500
1!
1%
b1001111 )
#24249903000
0!
0%
#24291569500
1!
1%
b1010000 )
#24333236000
0!
0%
#24374902500
1!
1%
b1010001 )
#24416569000
0!
0%
#24458235500
1!
1%
b1010010 )
#24499902000
0!
0%
#24541568500
1!
1%
b1010011 )
#24583235000
0!
0%
#24624901500
1!
1%
b1010100 )
#24666568000
0!
0%
#24708234500
1!
1%
b1010101 )
#24749901000
0!
0%
#24791567500
1!
1%
b1010110 )
#24833234000
0!
0%
#24874900500
1!
1%
b1010111 )
#24916567000
0!
0%
#24958233500
1!
1%
b1011000 )
#24999900000
0!
0%
#25041566500
1!
1%
b1011001 )
#25083233000
0!
0%
#25124899500
1!
1%
b1011010 )
#25166566000
0!
0%
#25208232500
1!
1%
b1011011 )
#25249899000
0!
0%
#25291565500
1!
1%
b1011100 )
#25333232000
0!
0%
#25374898500
1!
1%
b1011101 )
#25416565000
0!
0%
#25458231500
1!
1%
b1011110 )
#25499898000
0!
0%
#25541564500
1!
1%
b1011111 )
#25583231000
0!
0%
#25624897500
1!
1%
b1100000 )
#25666564000
0!
0%
#25708230500
1!
1%
b1100001 )
#25749897000
0!
0%
#25791563500
1!
1%
b1100010 )
#25833230000
0!
0%
#25874896500
1!
1%
b1100011 )
#25916563000
0!
0%
#25958229500
1!
1%
b0 )
#25999896000
0!
0%
#26041562500
1!
1$
1%
1(
b1 )
#26083229000
0!
0%
#26124895500
1!
1%
b10 )
#26166562000
0!
0%
#26208228500
1!
1%
b11 )
#26249895000
0!
0%
#26291561500
1!
1%
b100 )
#26333228000
0!
0%
#26374894500
1!
1%
b101 )
#26416561000
0!
0%
#26458227500
1!
1%
b110 )
#26499894000
0!
0%
#26541560500
1!
1%
b111 )
#26583227000
0!
0%
#26624893500
1!
1%
b1000 )
#26666560000
0!
0%
#26708226500
1!
1%
b1001 )
#26749893000
0!
0%
#26791559500
1!
1%
b1010 )
#26833226000
0!
0%
#26874892500
1!
1%
b1011 )
#26916559000
0!
0%
#26958225500
1!
1%
b1100 )
#26999892000
0!
0%
#27041558500
1!
1%
b1101 )
#27083225000
0!
0%
#27124891500
1!
1%
b1110 )
#27166558000
0!
0%
#27208224500
1!
1%
b1111 )
#27249891000
0!
0%
#27291557500
1!
1%
b10000 )
#27333224000
0!
0%
#27374890500
1!
1%
b10001 )
#27416557000
0!
0%
#27458223500
1!
1%
b10010 )
#27499890000
0!
0%
#27541556500
1!
1%
b10011 )
#27583223000
0!
0%
#27624889500
1!
1%
b10100 )
#27666556000
0!
0%
#27708222500
1!
1%
b10101 )
#27749889000
0!
0%
#27791555500
1!
1%
b10110 )
#27833222000
0!
0%
#27874888500
1!
1%
b10111 )
#27916555000
0!
0%
#27958221500
1!
1%
b11000 )
#27999888000
0!
0%
#28041554500
1!
1%
b11001 )
#28083221000
0!
0%
#28124887500
1!
0$
1%
0(
b11010 )
#28166554000
0!
0%
#28208220500
1!
1%
b11011 )
#28249887000
0!
0%
#28291553500
1!
1%
b11100 )
#28333220000
0!
0%
#28374886500
1!
1%
b11101 )
#28416553000
0!
0%
#28458219500
1!
1%
b11110 )
#28499886000
0!
0%
#28541552500
1!
1%
b11111 )
#28583219000
0!
0%
#28624885500
1!
1%
b100000 )
#28666552000
0!
0%
#28708218500
1!
1%
b100001 )
#28749885000
0!
0%
#28791551500
1!
1%
b100010 )
#28833218000
0!
0%
#28874884500
1!
1%
b100011 )
#28916551000
0!
0%
#28958217500
1!
1%
b100100 )
#28999884000
0!
0%
#29041550500
1!
1%
b100101 )
#29083217000
0!
0%
#29124883500
1!
1%
b100110 )
#29166550000
0!
0%
#29208216500
1!
1%
b100111 )
#29249883000
0!
0%
#29291549500
1!
1%
b101000 )
#29333216000
0!
0%
#29374882500
1!
1%
b101001 )
#29416549000
0!
0%
#29458215500
1!
1%
b101010 )
#29499882000
0!
0%
#29541548500
1!
1%
b101011 )
#29583215000
0!
0%
#29624881500
1!
1%
b101100 )
#29666548000
0!
0%
#29708214500
1!
1%
b101101 )
#29749881000
0!
0%
#29791547500
1!
1%
b101110 )
#29833214000
0!
0%
#29874880500
1!
1%
b101111 )
#29916547000
0!
0%
#29958213500
1!
1%
b110000 )
#29999880000
0!
0%
#30041546500
1!
1%
b110001 )
#30083213000
0!
0%
#30124879500
1!
1%
b110010 )
#30166546000
0!
0%
#30208212500
1!
1%
b110011 )
#30249879000
0!
0%
#30291545500
1!
1%
b110100 )
#30333212000
0!
0%
#30374878500
1!
1%
b110101 )
#30416545000
0!
0%
#30458211500
1!
1%
b110110 )
#30499878000
0!
0%
#30541544500
1!
1%
b110111 )
#30583211000
0!
0%
#30624877500
1!
1%
b111000 )
#30666544000
0!
0%
#30708210500
1!
1%
b111001 )
#30749877000
0!
0%
#30791543500
1!
1%
b111010 )
#30833210000
0!
0%
#30874876500
1!
1%
b111011 )
#30916543000
0!
0%
#30958209500
1!
1%
b111100 )
#30999876000
0!
0%
#31041542500
1!
1%
b111101 )
#31083209000
0!
0%
#31124875500
1!
1%
b111110 )
#31166542000
0!
0%
#31208208500
1!
1%
b111111 )
#31249875000
0!
0%
#31291541500
1!
1%
b1000000 )
#31333208000
0!
0%
#31374874500
1!
1%
b1000001 )
#31416541000
0!
0%
#31458207500
1!
1%
b1000010 )
#31499874000
0!
0%
#31541540500
1!
1%
b1000011 )
#31583207000
0!
0%
#31624873500
1!
1%
b1000100 )
#31666540000
0!
0%
#31708206500
1!
1%
b1000101 )
#31749873000
0!
0%
#31791539500
1!
1%
b1000110 )
#31833206000
0!
0%
#31874872500
1!
1%
b1000111 )
#31916539000
0!
0%
#31958205500
1!
1%
b1001000 )
#31999872000
0!
0%
#32041538500
1!
1%
b1001001 )
#32083205000
0!
0%
#32124871500
1!
1%
b1001010 )
#32166538000
0!
0%
#32208204500
1!
1%
b1001011 )
#32249871000
0!
0%
#32291537500
1!
1%
b1001100 )
#32333204000
0!
0%
#32374870500
1!
1%
b1001101 )
#32416537000
0!
0%
#32458203500
1!
1%
b1001110 )
#32499870000
0!
0%
#32541536500
1!
1%
b1001111 )
#32583203000
0!
0%
#32624869500
1!
1%
b1010000 )
#32666536000
0!
0%
#32708202500
1!
1%
b1010001 )
#32749869000
0!
0%
#32791535500
1!
1%
b1010010 )
#32833202000
0!
0%
#32874868500
1!
1%
b1010011 )
#32916535000
0!
0%
#32958201500
1!
1%
b1010100 )
#32999868000
0!
0%
#33041534500
1!
1%
b1010101 )
#33083201000
0!
0%
#33124867500
1!
1%
b1010110 )
#33166534000
0!
0%
#33208200500
1!
1%
b1010111 )
#33249867000
0!
0%
#33291533500
1!
1%
b1011000 )
#33333200000
0!
0%
#33374866500
1!
1%
b1011001 )
#33416533000
0!
0%
#33458199500
1!
1%
b1011010 )
#33499866000
0!
0%
#33541532500
1!
1%
b1011011 )
#33583199000
0!
0%
#33624865500
1!
1%
b1011100 )
#33666532000
0!
0%
#33708198500
1!
1%
b1011101 )
#33749865000
0!
0%
#33791531500
1!
1%
b1011110 )
#33833198000
0!
0%
#33874864500
1!
1%
b1011111 )
#33916531000
0!
0%
#33958197500
1!
1%
b1100000 )
#33999864000
0!
0%
#34041530500
1!
1%
b1100001 )
#34083197000
0!
0%
#34124863500
1!
1%
b1100010 )
#34166530000
0!
0%
#34208196500
1!
1%
b1100011 )
#34249863000
0!
0%
#34291529500
1!
1%
b0 )
#34333196000
0!
0%
#34374862500
1!
1$
1%
1(
b1 )
#34416529000
0!
0%
#34458195500
1!
1%
b10 )
#34499862000
0!
0%
#34541528500
1!
1%
b11 )
#34583195000
0!
0%
#34624861500
1!
1%
b100 )
#34666528000
0!
0%
#34708194500
1!
1%
b101 )
#34749861000
0!
0%
#34791527500
1!
1%
b110 )
#34833194000
0!
0%
#34874860500
1!
1%
b111 )
#34916527000
0!
0%
#34958193500
1!
1%
b1000 )
#34999860000
0!
0%
#35041526500
1!
1%
b1001 )
#35083193000
0!
0%
#35124859500
1!
1%
b1010 )
#35166526000
0!
0%
#35208192500
1!
1%
b1011 )
#35249859000
0!
0%
#35291525500
1!
1%
b1100 )
#35333192000
0!
0%
#35374858500
1!
1%
b1101 )
#35416525000
0!
0%
#35458191500
1!
1%
b1110 )
#35499858000
0!
0%
#35541524500
1!
1%
b1111 )
#35583191000
0!
0%
#35624857500
1!
1%
b10000 )
#35666524000
0!
0%
#35708190500
1!
1%
b10001 )
#35749857000
0!
0%
#35791523500
1!
1%
b10010 )
#35833190000
0!
0%
#35874856500
1!
1%
b10011 )
#35916523000
0!
0%
#35958189500
1!
1%
b10100 )
#35999856000
0!
0%
#36041522500
1!
1%
b10101 )
#36083189000
0!
0%
#36124855500
1!
1%
b10110 )
#36166522000
0!
0%
#36208188500
1!
1%
b10111 )
#36249855000
0!
0%
#36291521500
1!
1%
b11000 )
#36333188000
0!
0%
#36374854500
1!
1%
b11001 )
#36416521000
0!
0%
#36458187500
1!
0$
1%
0(
b11010 )
#36499854000
0!
0%
#36541520500
1!
1%
b11011 )
#36583187000
0!
0%
#36624853500
1!
1%
b11100 )
#36666520000
0!
0%
#36708186500
1!
1%
b11101 )
#36749853000
0!
0%
#36791519500
1!
1%
b11110 )
#36833186000
0!
0%
#36874852500
1!
1%
b11111 )
#36916519000
0!
0%
#36958185500
1!
1%
b100000 )
#36999852000
0!
0%
#37041518500
1!
1%
b100001 )
#37083185000
0!
0%
#37124851500
1!
1%
b100010 )
#37166518000
0!
0%
#37208184500
1!
1%
b100011 )
#37249851000
0!
0%
#37291517500
1!
1%
b100100 )
